GRT.py
_GRT.cpython-39-darwin.so
blackhc.GRT-0.2.5.dev1.dist-info/METADATA
blackhc.GRT-0.2.5.dev1.dist-info/WHEEL
blackhc.GRT-0.2.5.dev1.dist-info/top_level.txt
blackhc.GRT-0.2.5.dev1.dist-info/RECORD
