Metadata-Version: 2.1
Name: blackhc.GRT
Version: 0.2.5.dev1
Summary: Python bindings for the Gesture Recognition Toolkit (GRT)
Author: Nick Gillian
Requires-Dist: numpy
Requires-Dist: swig
